{
    "success": true,
    "message": "Cities retrieved successfully",
    "data": {
        "cities": [
            {
                "avg_pay_rate_usd_hour": "55.1",
                "climate_avg_temp_c": "24.8",
                "climate_summary": "Temperate",
                "cost_pct_coworking": "13.09",
                "cost_pct_dining": "10.34",
                "cost_pct_groceries": "20.38",
                "cost_pct_other": "18.23",
                "cost_pct_rent": "32.29",
                "cost_pct_transport": "5.67",
                "country": "Malaysia",
                "currency": "USD",
                "description": null,
                "housing_coliving_usd_month": "1081.5",
                "housing_one_bed_usd_month": "2056.37",
                "housing_studio_usd_month": "1464.76",
                "id": "d2ae98ca73654990a405e604",
                "internet_speed": "139.2 Mbps Mbps",
                "last_updated": "2025-08-16T11:34:44.860449",
                "lifestyle_tags": "[\"historic\", \"foodie\"]",
                "ml_enhanced": true,
                "monthly_cost_usd": "943.65",
                "name": "Johor Bahru",
                "nightlife_rating": "4.96",
                "predicted_score": 0.897815823931422,
                "safety_score": "66.88",
                "slug": "johor-bahru",
                "transport_rating": "3.91",
                "travel_flight_from_usd": "496.89",
                "travel_hotel_usd_week": "952.9",
                "travel_local_transport_usd_week": "38.24",
                "weather_avg_temp_c": "24.8"
            },
            {
                "avg_pay_rate_usd_hour": "11.76",
                "climate_avg_temp_c": "26.0",
                "climate_summary": "Hot",
                "cost_pct_coworking": "10.08",
                "cost_pct_dining": "22.42",
                "cost_pct_groceries": "22.32",
                "cost_pct_other": "0.0",
                "cost_pct_rent": "36.02",
                "cost_pct_transport": "9.16",
                "country": "Argentina",
                "currency": "USD",
                "description": null,
                "housing_coliving_usd_month": "426.34",
                "housing_one_bed_usd_month": "2890.37",
                "housing_studio_usd_month": "1978.06",
                "id": "66647e194f974d2db9480fce",
                "internet_speed": "212.8 Mbps Mbps",
                "last_updated": "2025-08-16T11:34:44.860666",
                "lifestyle_tags": "[\"mountain\", \"outdoors\"]",
                "ml_enhanced": true,
                "monthly_cost_usd": "1043.53",
                "name": "Buenos Aires",
                "nightlife_rating": "2.75",
                "predicted_score": 0.8723912630488769,
                "safety_score": "72.15",
                "slug": "buenos-aires",
                "transport_rating": "2.2",
                "travel_flight_from_usd": "230.29",
                "travel_hotel_usd_week": "1315.31",
                "travel_local_transport_usd_week": "35.73",
                "weather_avg_temp_c": "26.0"
            },
            {
                "avg_pay_rate_usd_hour": "59.23",
                "climate_avg_temp_c": "22.0",
                "climate_summary": "Temperate",
                "cost_pct_coworking": "9.81",
                "cost_pct_dining": "24.89",
                "cost_pct_groceries": "10.76",
                "cost_pct_other": "14.86",
                "cost_pct_rent": "25.79",
                "cost_pct_transport": "13.89",
                "country": "Australia",
                "currency": "USD",
                "description": null,
                "housing_coliving_usd_month": "621.28",
                "housing_one_bed_usd_month": "1196.38",
                "housing_studio_usd_month": "857.51",
                "id": "2dad88f51fce4bab901c4074",
                "internet_speed": "223.3 Mbps Mbps",
                "last_updated": "2025-08-16T11:34:44.860866",
                "lifestyle_tags": "[\"digital-nomad\", \"coastal\"]",
                "ml_enhanced": true,
                "monthly_cost_usd": "1801.5",
                "name": "Sydney",
                "nightlife_rating": "3.88",
                "predicted_score": 0.8580202986314013,
                "safety_score": "73.98",
                "slug": "sydney",
                "transport_rating": "3.7",
                "travel_flight_from_usd": "206.23",
                "travel_hotel_usd_week": "858.26",
                "travel_local_transport_usd_week": "42.97",
                "weather_avg_temp_c": "22.0"
            },
            {
                "avg_pay_rate_usd_hour": "52.22",
                "climate_avg_temp_c": "24.0",
                "climate_summary": "Temperate",
                "cost_pct_coworking": "6.11",
                "cost_pct_dining": "14.77",
                "cost_pct_groceries": "18.94",
                "cost_pct_other": "1.5",
                "cost_pct_rent": "43.69",
                "cost_pct_transport": "14.98",
                "country": "Pakistan",
                "currency": "USD",
                "description": null,
                "housing_coliving_usd_month": "328.94",
                "housing_one_bed_usd_month": "723.74",
                "housing_studio_usd_month": "508.88",
                "id": "1822cd81f5174e31b9db445a",
                "internet_speed": "84.2 Mbps Mbps",
                "last_updated": "2025-08-16T11:34:44.861060",
                "lifestyle_tags": "[\"nightlife\", \"startup\"]",
                "ml_enhanced": true,
                "monthly_cost_usd": "1018.59",
                "name": "Islamabad",
                "nightlife_rating": "2.91",
                "predicted_score": 0.8109194914963979,
                "safety_score": "62.87",
                "slug": "islamabad",
                "transport_rating": "2.94",
                "travel_flight_from_usd": "189.64",
                "travel_hotel_usd_week": "856.77",
                "travel_local_transport_usd_week": "23.44",
                "weather_avg_temp_c": "24.0"
            },
            {
                "avg_pay_rate_usd_hour": "34.99",
                "climate_avg_temp_c": "26.1",
                "climate_summary": "Hot",
                "cost_pct_coworking": "6.47",
                "cost_pct_dining": "17.78",
                "cost_pct_groceries": "21.91",
                "cost_pct_other": "21.78",
                "cost_pct_rent": "26.75",
                "cost_pct_transport": "5.32",
                "country": "United Arab Emirates",
                "currency": "USD",
                "description": null,
                "housing_coliving_usd_month": "838.86",
                "housing_one_bed_usd_month": "700.13",
                "housing_studio_usd_month": "438.55",
                "id": "b11149660c6c49a8bdf0af52",
                "internet_speed": "122.7 Mbps Mbps",
                "last_updated": "2025-08-16T11:34:44.861401",
                "lifestyle_tags": "[\"historic\", \"foodie\"]",
                "ml_enhanced": true,
                "monthly_cost_usd": "1125.37",
                "name": "Dubai",
                "nightlife_rating": "4.56",
                "predicted_score": 0.7968840749475232,
                "safety_score": "71.83",
                "slug": "dubai",
                "transport_rating": "4.91",
                "travel_flight_from_usd": "323.63",
                "travel_hotel_usd_week": "1134.59",
                "travel_local_transport_usd_week": "22.18",
                "weather_avg_temp_c": "26.1"
            },
            {
                "avg_pay_rate_usd_hour": "15.93",
                "climate_avg_temp_c": "20.4",
                "climate_summary": "Temperate",
                "cost_pct_coworking": "6.51",
                "cost_pct_dining": "10.5",
                "cost_pct_groceries": "20.21",
                "cost_pct_other": "23.1",
                "cost_pct_rent": "31.31",
                "cost_pct_transport": "8.37",
                "country": "Portugal",
                "currency": "USD",
                "description": null,
                "housing_coliving_usd_month": "300.05",
                "housing_one_bed_usd_month": "715.58",
                "housing_studio_usd_month": "631.75",
                "id": "8f990eb9983044cbaf9428f4",
                "internet_speed": "235.7 Mbps Mbps",
                "last_updated": "2025-08-16T11:34:44.861623",
                "lifestyle_tags": "[\"nightlife\", \"startup\"]",
                "ml_enhanced": true,
                "monthly_cost_usd": "2670.33",
                "name": "Porto",
                "nightlife_rating": "4.47",
                "predicted_score": 0.6367046308293638,
                "safety_score": "86.81",
                "slug": "porto",
                "transport_rating": "4.4",
                "travel_flight_from_usd": "736.16",
                "travel_hotel_usd_week": "229.89",
                "travel_local_transport_usd_week": "58.1",
                "weather_avg_temp_c": "20.4"
            },
            {
                "avg_pay_rate_usd_hour": "17.49",
                "climate_avg_temp_c": "17.0",
                "climate_summary": "Temperate",
                "cost_pct_coworking": "10.73",
                "cost_pct_dining": "19.21",
                "cost_pct_groceries": "19.78",
                "cost_pct_other": "13.01",
                "cost_pct_rent": "29.51",
                "cost_pct_transport": "7.75",
                "country": "Canada",
                "currency": "USD",
                "description": null,
                "housing_coliving_usd_month": "646.29",
                "housing_one_bed_usd_month": "3007.37",
                "housing_studio_usd_month": "1984.84",
                "id": "2c5bf8d7db704b14bcf1147a",
                "internet_speed": "73.5 Mbps Mbps",
                "last_updated": "2025-08-16T11:34:44.861829",
                "lifestyle_tags": "[\"nightlife\", \"startup\"]",
                "ml_enhanced": true,
                "monthly_cost_usd": "1119.18",
                "name": "Toronto",
                "nightlife_rating": "4.04",
                "predicted_score": 0.6271228987264312,
                "safety_score": "65.8",
                "slug": "toronto",
                "transport_rating": "4.75",
                "travel_flight_from_usd": "424.48",
                "travel_hotel_usd_week": "1011.06",
                "travel_local_transport_usd_week": "86.14",
                "weather_avg_temp_c": "17.0"
            },
            {
                "avg_pay_rate_usd_hour": "50.2",
                "climate_avg_temp_c": "22.0",
                "climate_summary": "Temperate",
                "cost_pct_coworking": "8.84",
                "cost_pct_dining": "19.39",
                "cost_pct_groceries": "20.83",
                "cost_pct_other": "1.61",
                "cost_pct_rent": "36.1",
                "cost_pct_transport": "13.24",
                "country": "Poland",
                "currency": "USD",
                "description": null,
                "housing_coliving_usd_month": "364.71",
                "housing_one_bed_usd_month": "1830.9",
                "housing_studio_usd_month": "1295.65",
                "id": "d0ba06c6972541f79152dbcb",
                "internet_speed": "252.5 Mbps Mbps",
                "last_updated": "2025-08-16T11:34:44.862030",
                "lifestyle_tags": "[\"digital-nomad\", \"coastal\"]",
                "ml_enhanced": true,
                "monthly_cost_usd": "983.05",
                "name": "Warsaw",
                "nightlife_rating": "3.0",
                "predicted_score": 0.5889954692126964,
                "safety_score": "45.69",
                "slug": "warsaw",
                "transport_rating": "4.84",
                "travel_flight_from_usd": "962.83",
                "travel_hotel_usd_week": "1488.71",
                "travel_local_transport_usd_week": "83.7",
                "weather_avg_temp_c": "22.0"
            },
            {
                "avg_pay_rate_usd_hour": "42.65",
                "climate_avg_temp_c": "25.8",
                "climate_summary": "Hot",
                "cost_pct_coworking": "9.55",
                "cost_pct_dining": "11.77",
                "cost_pct_groceries": "11.39",
                "cost_pct_other": "20.9",
                "cost_pct_rent": "31.61",
                "cost_pct_transport": "14.79",
                "country": "France",
                "currency": "USD",
                "description": null,
                "housing_coliving_usd_month": "519.97",
                "housing_one_bed_usd_month": "2751.2",
                "housing_studio_usd_month": "1962.62",
                "id": "590b56476e8f473b8045014d",
                "internet_speed": "48.9 Mbps Mbps",
                "last_updated": "2025-08-16T11:34:44.862364",
                "lifestyle_tags": "[\"mountain\", \"outdoors\"]",
                "ml_enhanced": true,
                "monthly_cost_usd": "2640.77",
                "name": "Nice",
                "nightlife_rating": "2.99",
                "predicted_score": 0.5334943891196927,
                "safety_score": "86.2",
                "slug": "nice",
                "transport_rating": "2.06",
                "travel_flight_from_usd": "1146.56",
                "travel_hotel_usd_week": "238.2",
                "travel_local_transport_usd_week": "61.12",
                "weather_avg_temp_c": "25.8"
            },
            {
                "avg_pay_rate_usd_hour": "27.0",
                "climate_avg_temp_c": "22.9",
                "climate_summary": "Temperate",
                "cost_pct_coworking": "13.33",
                "cost_pct_dining": "11.37",
                "cost_pct_groceries": "21.3",
                "cost_pct_other": "0.88",
                "cost_pct_rent": "39.53",
                "cost_pct_transport": "13.6",
                "country": "Poland",
                "currency": "USD",
                "description": null,
                "housing_coliving_usd_month": "327.71",
                "housing_one_bed_usd_month": "1272.82",
                "housing_studio_usd_month": "1096.58",
                "id": "3101bd4dad504e20909392f9",
                "internet_speed": "56.1 Mbps Mbps",
                "last_updated": "2025-08-16T11:34:44.862976",
                "lifestyle_tags": "[\"historic\", \"foodie\"]",
                "ml_enhanced": true,
                "monthly_cost_usd": "1478.79",
                "name": "Kraków",
                "nightlife_rating": "2.75",
                "predicted_score": 0.52740863917574,
                "safety_score": "60.01",
                "slug": "kraków",
                "transport_rating": "4.27",
                "travel_flight_from_usd": "1078.83",
                "travel_hotel_usd_week": "423.1",
                "travel_local_transport_usd_week": "81.36",
                "weather_avg_temp_c": "22.9"
            },
            {
                "avg_pay_rate_usd_hour": "35.26",
                "climate_avg_temp_c": "20.1",
                "climate_summary": "Temperate",
                "cost_pct_coworking": "6.86",
                "cost_pct_dining": "23.37",
                "cost_pct_groceries": "17.37",
                "cost_pct_other": "7.96",
                "cost_pct_rent": "38.63",
                "cost_pct_transport": "5.81",
                "country": "Japan",
                "currency": "USD",
                "description": null,
                "housing_coliving_usd_month": "1119.59",
                "housing_one_bed_usd_month": "769.29",
                "housing_studio_usd_month": "501.49",
                "id": "56ebbbbe45294c71964186d2",
                "internet_speed": "185.8 Mbps Mbps",
                "last_updated": "2025-08-16T11:34:44.863513",
                "lifestyle_tags": "[\"digital-nomad\", \"coastal\"]",
                "ml_enhanced": true,
                "monthly_cost_usd": "2270.48",
                "name": "Kyoto",
                "nightlife_rating": "4.02",
                "predicted_score": 0.5056107620120227,
                "safety_score": "77.14",
                "slug": "kyoto",
                "transport_rating": "4.09",
                "travel_flight_from_usd": "1336.56",
                "travel_hotel_usd_week": "1458.3",
                "travel_local_transport_usd_week": "39.91",
                "weather_avg_temp_c": "20.1"
            },
            {
                "avg_pay_rate_usd_hour": "31.09",
                "climate_avg_temp_c": "22.2",
                "climate_summary": "Temperate",
                "cost_pct_coworking": "8.59",
                "cost_pct_dining": "19.11",
                "cost_pct_groceries": "14.0",
                "cost_pct_other": "12.37",
                "cost_pct_rent": "32.35",
                "cost_pct_transport": "13.59",
                "country": "Australia",
                "currency": "USD",
                "description": null,
                "housing_coliving_usd_month": "574.27",
                "housing_one_bed_usd_month": "513.0",
                "housing_studio_usd_month": "427.2",
                "id": "f403ca74756f4d6780ff298f",
                "internet_speed": "196.0 Mbps Mbps",
                "last_updated": "2025-08-16T11:34:44.863856",
                "lifestyle_tags": "[\"nightlife\", \"startup\"]",
                "ml_enhanced": true,
                "monthly_cost_usd": "1537.38",
                "name": "Melbourne",
                "nightlife_rating": "2.77",
                "predicted_score": 0.47940023884599686,
                "safety_score": "54.99",
                "slug": "melbourne",
                "transport_rating": "3.17",
                "travel_flight_from_usd": "534.24",
                "travel_hotel_usd_week": "550.36",
                "travel_local_transport_usd_week": "45.13",
                "weather_avg_temp_c": "22.2"
            },
            {
                "avg_pay_rate_usd_hour": "46.98",
                "climate_avg_temp_c": "23.5",
                "climate_summary": "Temperate",
                "cost_pct_coworking": "8.65",
                "cost_pct_dining": "13.38",
                "cost_pct_groceries": "24.54",
                "cost_pct_other": "0.0",
                "cost_pct_rent": "40.07",
                "cost_pct_transport": "13.36",
                "country": "Greece",
                "currency": "USD",
                "description": null,
                "housing_coliving_usd_month": "531.81",
                "housing_one_bed_usd_month": "1821.91",
                "housing_studio_usd_month": "1314.72",
                "id": "b3cc5095051f409fb5f959ca",
                "internet_speed": "11.0 Mbps Mbps",
                "last_updated": "2025-08-16T11:34:44.864126",
                "lifestyle_tags": "[\"digital-nomad\", \"coastal\"]",
                "ml_enhanced": true,
                "monthly_cost_usd": "1068.92",
                "name": "Athens",
                "nightlife_rating": "3.41",
                "predicted_score": 0.4792980155377649,
                "safety_score": "47.27",
                "slug": "athens",
                "transport_rating": "3.96",
                "travel_flight_from_usd": "489.37",
                "travel_hotel_usd_week": "1235.18",
                "travel_local_transport_usd_week": "50.27",
                "weather_avg_temp_c": "23.5"
            },
            {
                "avg_pay_rate_usd_hour": "47.81",
                "climate_avg_temp_c": "20.5",
                "climate_summary": "Temperate",
                "cost_pct_coworking": "9.57",
                "cost_pct_dining": "21.6",
                "cost_pct_groceries": "15.49",
                "cost_pct_other": "0.0",
                "cost_pct_rent": "39.71",
                "cost_pct_transport": "13.64",
                "country": "Taiwan",
                "currency": "USD",
                "description": null,
                "housing_coliving_usd_month": "601.6",
                "housing_one_bed_usd_month": "1653.01",
                "housing_studio_usd_month": "1114.47",
                "id": "1ea4128e204d40e4bac65766",
                "internet_speed": "209.4 Mbps Mbps",
                "last_updated": "2025-08-16T11:34:44.864373",
                "lifestyle_tags": "[\"nightlife\", \"startup\"]",
                "ml_enhanced": true,
                "monthly_cost_usd": "2437.32",
                "name": "Taipei",
                "nightlife_rating": "2.93",
                "predicted_score": 0.4543910475917981,
                "safety_score": "81.29",
                "slug": "taipei",
                "transport_rating": "4.28",
                "travel_flight_from_usd": "834.28",
                "travel_hotel_usd_week": "213.14",
                "travel_local_transport_usd_week": "45.14",
                "weather_avg_temp_c": "20.5"
            },
            {
                "avg_pay_rate_usd_hour": "30.31",
                "climate_avg_temp_c": "24.6",
                "climate_summary": "Temperate",
                "cost_pct_coworking": "12.16",
                "cost_pct_dining": "18.26",
                "cost_pct_groceries": "20.98",
                "cost_pct_other": "0.0",
                "cost_pct_rent": "40.82",
                "cost_pct_transport": "7.77",
                "country": "United States",
                "currency": "USD",
                "description": null,
                "housing_coliving_usd_month": "441.85",
                "housing_one_bed_usd_month": "2117.3",
                "housing_studio_usd_month": "1886.7",
                "id": "23828c78d27d4b0b9c4a2219",
                "internet_speed": "234.2 Mbps Mbps",
                "last_updated": "2025-08-16T11:34:44.865163",
                "lifestyle_tags": "[\"nightlife\", \"startup\"]",
                "ml_enhanced": true,
                "monthly_cost_usd": "1105.5",
                "name": "Washington",
                "nightlife_rating": "4.73",
                "predicted_score": 0.4447589635945596,
                "safety_score": "55.38",
                "slug": "washington",
                "transport_rating": "4.96",
                "travel_flight_from_usd": "698.73",
                "travel_hotel_usd_week": "909.27",
                "travel_local_transport_usd_week": "20.36",
                "weather_avg_temp_c": "24.6"
            },
            {
                "avg_pay_rate_usd_hour": "41.4",
                "climate_avg_temp_c": "24.1",
                "climate_summary": "Temperate",
                "cost_pct_coworking": "8.1",
                "cost_pct_dining": "17.82",
                "cost_pct_groceries": "16.61",
                "cost_pct_other": "13.37",
                "cost_pct_rent": "29.56",
                "cost_pct_transport": "14.54",
                "country": "India",
                "currency": "USD",
                "description": null,
                "housing_coliving_usd_month": "395.66",
                "housing_one_bed_usd_month": "1406.25",
                "housing_studio_usd_month": "921.76",
                "id": "e70e1c1ca46f45eaa6dae909",
                "internet_speed": "74.4 Mbps Mbps",
                "last_updated": "2025-08-16T11:34:44.865615",
                "lifestyle_tags": "[\"mountain\", \"outdoors\"]",
                "ml_enhanced": true,
                "monthly_cost_usd": "1203.53",
                "name": "Mumbai",
                "nightlife_rating": "4.15",
                "predicted_score": 0.42967991368553277,
                "safety_score": "46.39",
                "slug": "mumbai",
                "transport_rating": "2.82",
                "travel_flight_from_usd": "162.13",
                "travel_hotel_usd_week": "1202.23",
                "travel_local_transport_usd_week": "63.56",
                "weather_avg_temp_c": "24.1"
            },
            {
                "avg_pay_rate_usd_hour": "14.78",
                "climate_avg_temp_c": "12.0",
                "climate_summary": "Temperate",
                "cost_pct_coworking": "10.27",
                "cost_pct_dining": "18.12",
                "cost_pct_groceries": "19.35",
                "cost_pct_other": "5.82",
                "cost_pct_rent": "39.59",
                "cost_pct_transport": "6.85",
                "country": "France",
                "currency": "USD",
                "description": null,
                "housing_coliving_usd_month": "1228.91",
                "housing_one_bed_usd_month": "2792.6",
                "housing_studio_usd_month": "2126.61",
                "id": "b8a6ba2cc15f46f09f4eecda",
                "internet_speed": "107.1 Mbps Mbps",
                "last_updated": "2025-08-16T11:34:44.866078",
                "lifestyle_tags": "[\"digital-nomad\", \"coastal\"]",
                "ml_enhanced": true,
                "monthly_cost_usd": "1641.48",
                "name": "Paris",
                "nightlife_rating": "4.95",
                "predicted_score": 0.41621201751301173,
                "safety_score": "83.83",
                "slug": "paris",
                "transport_rating": "3.0",
                "travel_flight_from_usd": "291.91",
                "travel_hotel_usd_week": "442.24",
                "travel_local_transport_usd_week": "60.69",
                "weather_avg_temp_c": "12.0"
            },
            {
                "avg_pay_rate_usd_hour": "57.5",
                "climate_avg_temp_c": "21.2",
                "climate_summary": "Temperate",
                "cost_pct_coworking": "12.82",
                "cost_pct_dining": "13.77",
                "cost_pct_groceries": "12.49",
                "cost_pct_other": "15.49",
                "cost_pct_rent": "33.34",
                "cost_pct_transport": "12.09",
                "country": "Italy",
                "currency": "USD",
                "description": null,
                "housing_coliving_usd_month": "1487.52",
                "housing_one_bed_usd_month": "1270.12",
                "housing_studio_usd_month": "1110.67",
                "id": "3a028703906040a6adcb31c0",
                "internet_speed": "222.5 Mbps Mbps",
                "last_updated": "2025-08-16T11:34:44.866578",
                "lifestyle_tags": "[\"nightlife\", \"startup\"]",
                "ml_enhanced": true,
                "monthly_cost_usd": "2926.77",
                "name": "Rome",
                "nightlife_rating": "2.91",
                "predicted_score": 0.4131122875664364,
                "safety_score": "79.45",
                "slug": "rome",
                "transport_rating": "4.21",
                "travel_flight_from_usd": "1055.69",
                "travel_hotel_usd_week": "1302.85",
                "travel_local_transport_usd_week": "48.44",
                "weather_avg_temp_c": "21.2"
            },
            {
                "avg_pay_rate_usd_hour": "31.05",
                "climate_avg_temp_c": "20.7",
                "climate_summary": "Temperate",
                "cost_pct_coworking": "11.53",
                "cost_pct_dining": "19.17",
                "cost_pct_groceries": "21.76",
                "cost_pct_other": "7.01",
                "cost_pct_rent": "26.36",
                "cost_pct_transport": "14.18",
                "country": "Singapore",
                "currency": "USD",
                "description": null,
                "housing_coliving_usd_month": "1377.04",
                "housing_one_bed_usd_month": "1466.19",
                "housing_studio_usd_month": "1114.62",
                "id": "b9145a831d3b4f92a94e2099",
                "internet_speed": "257.7 Mbps Mbps",
                "last_updated": "2025-08-16T11:34:44.867165",
                "lifestyle_tags": "[\"nightlife\", \"startup\"]",
                "ml_enhanced": true,
                "monthly_cost_usd": "1779.97",
                "name": "Singapore",
                "nightlife_rating": "2.74",
                "predicted_score": 0.4067141435277032,
                "safety_score": "57.16",
                "slug": "singapore",
                "transport_rating": "2.1",
                "travel_flight_from_usd": "1206.47",
                "travel_hotel_usd_week": "1443.4",
                "travel_local_transport_usd_week": "28.64",
                "weather_avg_temp_c": "20.7"
            },
            {
                "avg_pay_rate_usd_hour": "41.04",
                "climate_avg_temp_c": "18.3",
                "climate_summary": "Temperate",
                "cost_pct_coworking": "10.43",
                "cost_pct_dining": "16.13",
                "cost_pct_groceries": "16.32",
                "cost_pct_other": "7.02",
                "cost_pct_rent": "42.03",
                "cost_pct_transport": "8.06",
                "country": "Denmark",
                "currency": "USD",
                "description": null,
                "housing_coliving_usd_month": "313.53",
                "housing_one_bed_usd_month": "1300.1",
                "housing_studio_usd_month": "1150.18",
                "id": "b0149b6511fd4b34aa138acf",
                "internet_speed": "98.7 Mbps Mbps",
                "last_updated": "2025-08-16T11:34:44.867460",
                "lifestyle_tags": "[\"nightlife\", \"startup\"]",
                "ml_enhanced": true,
                "monthly_cost_usd": "2389.95",
                "name": "Copenhagen",
                "nightlife_rating": "4.97",
                "predicted_score": 0.39013979940192406,
                "safety_score": "76.42",
                "slug": "copenhagen",
                "transport_rating": "4.16",
                "travel_flight_from_usd": "653.93",
                "travel_hotel_usd_week": "446.17",
                "travel_local_transport_usd_week": "47.49",
                "weather_avg_temp_c": "18.3"
            }
        ],
        "pagination": {
            "current_page": 10,
            "total_pages": 40,
            "total_items": 781,
            "items_per_page": 20,
            "has_next_page": true,
            "has_prev_page": true
        }
    }
}